AoikRegistryEditor-0.1.0.dist-info/DESCRIPTION.rst
AoikRegistryEditor-0.1.0.dist-info/METADATA
AoikRegistryEditor-0.1.0.dist-info/RECORD
AoikRegistryEditor-0.1.0.dist-info/WHEEL
AoikRegistryEditor-0.1.0.dist-info/entry_points.txt
AoikRegistryEditor-0.1.0.dist-info/metadata.json
AoikRegistryEditor-0.1.0.dist-info/top_level.txt
aoikregistryeditor/__init__.py
aoikregistryeditor/__main__.py
aoikregistryeditor/aoikargutil.py
aoikregistryeditor/aoikimportutil.py
aoikregistryeditor/aoikregistryeditor.py
aoikregistryeditor/eventor.py
aoikregistryeditor/field_editor_config.py
aoikregistryeditor/mediator.py
aoikregistryeditor/menu_config.py
aoikregistryeditor/registry.py
aoikregistryeditor/registry_editor.py
aoikregistryeditor/ui_config.py
aoikregistryeditor/static/__init__.py
aoikregistryeditor/static/field_add_active.png
aoikregistryeditor/static/field_add_hover.png
aoikregistryeditor/static/field_add_normal.png
aoikregistryeditor/static/field_del_active.png
aoikregistryeditor/static/field_del_hover.png
aoikregistryeditor/static/field_del_normal.png
aoikregistryeditor/static/field_load_active.png
aoikregistryeditor/static/field_load_hover.png
aoikregistryeditor/static/field_load_normal.png
aoikregistryeditor/static/field_save_active.png
aoikregistryeditor/static/field_save_hover.png
aoikregistryeditor/static/field_save_normal.png
aoikregistryeditor/static/path_bar_label_disabled.png
aoikregistryeditor/static/path_bar_label_normal.png
aoikregistryeditor/tkinterutil/__init__.py
aoikregistryeditor/tkinterutil/eventor.py
aoikregistryeditor/tkinterutil/label.py
aoikregistryeditor/tkinterutil/listbox.py
aoikregistryeditor/tkinterutil/menu.py
aoikregistryeditor/tkinterutil/text.py
aoikregistryeditor/tkinterutil/toplevel.py
aoikregistryeditor/tkinterutil/vidget.py
