Metadata-Version: 2.0
Name: AoikRegistryEditor
Version: 0.1.0
Summary: A customizable registry editor.
Home-page: https://github.com/AoiKuiyuyou/AoikRegistryEditor
Author: Aoi.Kuiyuyou
Author-email: aoi.kuiyuyou@google.com
License: MIT
Keywords: registry editor
Platform: UNKNOWN
Classifier: Development Status :: 3 - Alpha
Classifier: Environment :: Console
Classifier: Intended Audience :: Developers
Classifier: License :: OSI Approved :: MIT License
Classifier: Operating System :: Microsoft :: Windows
Classifier: Programming Language :: Python :: 3
Classifier: Programming Language :: Python :: 3.5
